myo/__init__.py
myo/_device_listener.py
myo/_ffi.py
myo/libmyo.h
myo/macaddr.py
myo/math.py
myo/utils.py
myo/types/__init__.py
myo/types/macaddr.py
myo/types/math.py
myo_python-1.0.5.dist-info/LICENSE.txt
myo_python-1.0.5.dist-info/METADATA
myo_python-1.0.5.dist-info/WHEEL
myo_python-1.0.5.dist-info/top_level.txt
myo_python-1.0.5.dist-info/zip-safe
myo_python-1.0.5.dist-info/RECORD
