Metadata-Version: 2.1
Name: myo-python
Version: 1.0.5
Summary: Python bindings for the Thalmic Labs Myo SDK.
Home-page: https://github.com/NiklasRosenstein/myo-python
Author: Niklas Rosenstein
Author-email: rosensteinniklas@gmail.com
License: MIT
Platform: UNKNOWN
Requires-Python: >=3.5.0,<4.0.0
Requires-Dist: cffi (<2.0.0,>=1.11.5)
Requires-Dist: six (<2.0.0,>=1.11.0)
